sqlite3mtp/__init__.py
sqlite3mtp/importdata.py
sqlite3mtp/select.py
sqlite3mtp-0.0.3.dist-info/LICENSE
sqlite3mtp-0.0.3.dist-info/METADATA
sqlite3mtp-0.0.3.dist-info/WHEEL
sqlite3mtp-0.0.3.dist-info/top_level.txt
sqlite3mtp-0.0.3.dist-info/RECORD
