Metadata-Version: 2.1
Name: sqlite3mtp
Version: 0.0.3
Summary: to manipulate a sqlite3 database
Home-page: https://github.com/laishuhan/sqlite3mtp
Author: laishuhan
Author-email: 3027826050@qq.com
Classifier: Programming Language :: Python :: 3
Classifier: License :: OSI Approved :: MIT License
Classifier: Operating System :: OS Independent
License-File: LICENSE
